regexr/__init__.py
regexr/string.py
regexr-0.0.2.dist-info/WHEEL
regexr-0.0.2.dist-info/METADATA
regexr-0.0.2.dist-info/RECORD
