Metadata-Version: 2.1
Name: regexr
Version: 0.0.2
Summary: Regular expressions for humans
License: MIT
Author: pwwang
Author-email: pwwang@pwwang.com
Requires-Python: >=3.7,<4.0
Classifier: License :: OSI Approved :: MIT License
Classifier: Programming Language :: Python :: 3
Classifier: Programming Language :: Python :: 3.10
Classifier: Programming Language :: Python :: 3.7
Classifier: Programming Language :: Python :: 3.8
Classifier: Programming Language :: Python :: 3.9
